groupdups/__init__.py
groupdups-0.1.0.dist-info/LICENSE
groupdups-0.1.0.dist-info/METADATA
groupdups-0.1.0.dist-info/WHEEL
groupdups-0.1.0.dist-info/top_level.txt
groupdups-0.1.0.dist-info/RECORD
